stacked_seds/__init__.py
stacked_seds/photometry.py
stacked_seds/plotting.py
stacked_seds/stacking.py
stacked_seds/utils.py
stacked_seds/scripts/__init__.py
stacked_seds/scripts/run_photometry.py
stacked_seds/scripts/run_stacking.py
stacked_seds-1.0.1.dist-info/licenses/LICENSE
stacked_seds-1.0.1.dist-info/METADATA
stacked_seds-1.0.1.dist-info/WHEEL
stacked_seds-1.0.1.dist-info/entry_points.txt
stacked_seds-1.0.1.dist-info/top_level.txt
stacked_seds-1.0.1.dist-info/RECORD
