Metadata-Version: 2.4
Name: stacked-seds
Version: 1.0.1
Summary: A Python package to stack faint galaxy images and prepare them for SED analysis
Author: O. Abraham, C. Chapman, E. Garcia
Author-email: "R. Trainor" <ryan.trainor@fandm.edu>
Maintainer-email: "R. Trainor" <ryan.trainor@fandm.edu>
License: MIT
Project-URL: Homepage, https://github.com/ryantrainor/stacked-seds
Project-URL: Documentation, https://stacked-seds.readthedocs.io/
Project-URL: Repository, https://github.com/ryantrainor/stacked-seds
Project-URL: Bug Tracker, https://github.com/ryantrainor/stacked-seds/issues
Keywords: astronomy,astrophysics,galaxy,photometry,sed,stacking,image-processing
Classifier: Development Status :: 4 - Beta
Classifier: Intended Audience :: Science/Research
Classifier: Topic :: Scientific/Engineering :: Astronomy
Classifier: Programming Language :: Python :: 3
Classifier: Programming Language :: Python :: 3.8
Classifier: Programming Language :: Python :: 3.9
Classifier: Programming Language :: Python :: 3.10
Classifier: Programming Language :: Python :: 3.11
Classifier: Operating System :: OS Independent
Requires-Python: >=3.8
License-File: LICENSE
Requires-Dist: numpy>=1.20.0
Requires-Dist: scipy>=1.7.0
Requires-Dist: matplotlib>=3.5.0
Requires-Dist: astropy>=5.0.0
Requires-Dist: pyyaml>=6.0
Requires-Dist: photutils>=1.5.0
Provides-Extra: dev
Requires-Dist: black>=22.0; extra == "dev"
Requires-Dist: flake8>=4.0; extra == "dev"
Requires-Dist: pytest>=6.0; extra == "dev"
Requires-Dist: pytest-cov>=3.0; extra == "dev"
Requires-Dist: pre-commit>=2.0; extra == "dev"
Provides-Extra: docs
Requires-Dist: sphinx>=4.0; extra == "docs"
Requires-Dist: sphinx-rtd-theme>=1.0; extra == "docs"
Requires-Dist: sphinx-autoapi>=2.0; extra == "docs"
Requires-Dist: myst-parser>=0.18; extra == "docs"
Dynamic: license-file
